{
  "fixtures": {
    "24": [
      ["AFC Bournemo-Chelsea", ""],
      ["Arsenal-Cardiff City", ""],
      ["Fulham-Brighton   H", ""],
      ["Huddersfield-Everton", ""],
      ["Wolverhampto-West Ham Uni", ""],
      ["Manchester U-Burnley", ""],
      ["Newcastle Un-Manchester C", ""],
      ["Southampton-Crystal Pala", ""],
      ["Liverpool-Leicester Ci", ""],
      ["Tottenham Ho-Watford", ""]
    ],
    "25": [
      ["Brighton   H-Watford", ""],
      ["Burnley-Southampton", ""],
      ["Cardiff City-AFC Bournemo", ""],
      ["Chelsea-Huddersfield", ""],
      ["Crystal Pala-Fulham", ""],
      ["Everton-Wolverhampto", ""],
      ["Leicester Ci-Manchester U", ""],
      ["Manchester C-Arsenal", ""],
      ["Tottenham Ho-Newcastle Un", ""],
      ["West Ham Uni-Liverpool", ""]
    ],
    "26": [
      ["Brighton   H-Burnley", ""],
      ["Crystal Pala-West Ham Uni", ""],
      ["Fulham-Manchester U", ""],
      ["Huddersfield-Arsenal", ""],
      ["Liverpool-AFC Bournemo", ""],
      ["Manchester C-Chelsea", ""],
      ["Southampton-Cardiff City", ""],
      ["Tottenham Ho-Leicester Ci", ""],
      ["Watford-Everton", ""],
      ["Wolverhampto-Newcastle Un", ""]
    ],
    "27": [
      ["AFC Bournemo-Wolverhampto", ""],
      ["Arsenal-Southampton", ""],
      ["Burnley-Tottenham Ho", ""],
      ["Cardiff City-Watford", ""],
      ["Chelsea-Brighton   H", ""],
      ["Everton-Manchester C", ""],
      ["Leicester Ci-Crystal Pala", ""],
      ["Manchester U-Liverpool", ""],
      ["Newcastle Un-Huddersfield", ""],
      ["West Ham Uni-Fulham", ""]
    ],
    "20": [
      ["Brighton   H-Everton", ""],
      ["Burnley-West Ham Uni", ""],
      ["Crystal Pala-Chelsea", ""],
      ["Fulham-Huddersfield", ""],
      ["Leicester Ci-Cardiff City", ""],
      ["Liverpool-Arsenal", ""],
      ["Manchester U-AFC Bournemo", ""],
      ["Southampton-Manchester C", ""],
      ["Tottenham Ho-Wolverhampto", ""],
      ["Watford-Newcastle Un", ""]
    ],
    "21": [
      ["AFC Bournemo-Watford", ""],
      ["Arsenal-Fulham", ""],
      ["Cardiff City-Tottenham Ho", ""],
      ["Chelsea-Southampton", ""],
      ["Everton-Leicester Ci", ""],
      ["Huddersfield-Burnley", ""],
      ["Manchester C-Liverpool", ""],
      ["Newcastle Un-Manchester U", ""],
      ["West Ham Uni-Brighton   H", ""],
      ["Wolverhampto-Crystal Pala", ""]
    ],
    "22": [
      ["Brighton   H-Liverpool", ""],
      ["Burnley-Fulham", ""],
      ["Cardiff City-Huddersfield", ""],
      ["Chelsea-Newcastle Un", ""],
      ["Crystal Pala-Watford", ""],
      ["Everton-AFC Bournemo", ""],
      ["Leicester Ci-Southampton", ""],
      ["Manchester C-Wolverhampto", ""],
      ["Tottenham Ho-Manchester U", ""],
      ["West Ham Uni-Arsenal", ""]
    ],
    "23": [
      ["AFC Bournemo-West Ham Uni", ""],
      ["Arsenal-Chelsea", ""],
      ["Fulham-Tottenham Ho", ""],
      ["Huddersfield-Manchester C", ""],
      ["Liverpool-Crystal Pala", ""],
      ["Manchester U-Brighton   H", ""],
      ["Newcastle Un-Cardiff City", ""],
      ["Southampton-Everton", ""],
      ["Watford-Burnley", ""],
      ["Wolverhampto-Leicester Ci", ""]
    ],
    "28": [
      ["Arsenal-AFC Bournemo", ""],
      ["Cardiff City-Everton", ""],
      ["Huddersfield-Wolverhampto", ""],
      ["Leicester Ci-Brighton   H", ""],
      ["Crystal Pala-Manchester U", ""],
      ["Chelsea-Tottenham Ho", ""],
      ["Newcastle Un-Burnley", ""],
      ["Southampton-Fulham", ""],
      ["Liverpool-Watford", ""],
      ["Manchester C-West Ham Uni", ""]
    ],
    "29": [
      ["AFC Bournemo-Manchester C", ""],
      ["Brighton   H-Huddersfield", ""],
      ["Burnley-Crystal Pala", ""],
      ["Everton-Liverpool", ""],
      ["Fulham-Chelsea", ""],
      ["Manchester U-Southampton", ""],
      ["Tottenham Ho-Arsenal", ""],
      ["Watford-Leicester Ci", ""],
      ["West Ham Uni-Newcastle Un", ""],
      ["Wolverhampto-Cardiff City", ""]
    ],
    "1": [
      ["Manchester U-Leicester Ci", "2-1"],
      ["Newcastle Un-Tottenham Ho", "1-2"],
      ["AFC Bournemo-Cardiff City", "2-0"],
      ["Fulham-Crystal Pala", "0-2"],
      ["Huddersfield-Chelsea", "0-3"],
      ["Watford-Brighton   H", "2-0"],
      ["Wolverhampto-Everton", "2-2"],
      ["Liverpool-West Ham Uni", "4-0"],
      ["Southampton-Burnley", "0-0"],
      ["Arsenal-Manchester C", "0-2"]
    ],
    "3": [
      ["Wolverhampto-Manchester C", "1-1"],
      ["AFC Bournemo-Everton", "2-2"],
      ["Arsenal-West Ham Uni", "3-1"],
      ["Fulham-Burnley", "4-2"],
      ["Huddersfield-Cardiff City", "0-0"],
      ["Southampton-Leicester Ci", "1-2"],
      ["Liverpool-Brighton   H", "1-0"],
      ["Watford-Crystal Pala", "2-1"],
      ["Newcastle Un-Chelsea", "1-2"],
      ["Manchester U-Tottenham Ho", "0-3"]
    ],
    "2": [
      ["Cardiff City-Newcastle Un", "0-0"],
      ["Burnley-Watford", "1-3"],
      ["Everton-Southampton", "2-1"],
      ["Leicester Ci-Wolverhampto", "2-0"],
      ["Tottenham Ho-Fulham", "3-1"],
      ["West Ham Uni-AFC Bournemo", "1-2"],
      ["Chelsea-Arsenal", "3-2"],
      ["Manchester C-Huddersfield", "6-1"],
      ["Brighton   H-Manchester U", "3-2"],
      ["Crystal Pala-Liverpool", "0-2"]
    ],
    "5": [
      ["Tottenham Ho-Liverpool", "1-2"],
      ["AFC Bournemo-Leicester Ci", "4-2"],
      ["Chelsea-Cardiff City", "4-1"],
      ["Huddersfield-Crystal Pala", "0-1"],
      ["Manchester C-Fulham", "3-0"],
      ["Newcastle Un-Arsenal", "1-2"],
      ["Watford-Manchester U", "1-2"],
      ["Wolverhampto-Burnley", "1-0"],
      ["Everton-West Ham Uni", "1-3"],
      ["Southampton-Brighton   H", "2-2"]
    ],
    "4": [
      ["Leicester Ci-Liverpool", "1-2"],
      ["Brighton   H-Fulham", "2-2"],
      ["Burnley-Manchester U", "0-2"],
      ["Chelsea-AFC Bournemo", "2-0"],
      ["Crystal Pala-Southampton", "0-2"],
      ["Everton-Huddersfield", "1-1"],
      ["West Ham Uni-Wolverhampto", "0-1"],
      ["Manchester C-Newcastle Un", "2-1"],
      ["Cardiff City-Arsenal", "2-3"],
      ["Watford-Tottenham Ho", "2-1"]
    ],
    "7": [
      ["West Ham Uni-Manchester U", "3-1"],
      ["Arsenal-Watford", "2-0"],
      ["Everton-Fulham", "3-0"],
      ["Huddersfield-Tottenham Ho", "0-2"],
      ["Manchester C-Brighton   H", "2-0"],
      ["Newcastle Un-Leicester Ci", "0-2"],
      ["Wolverhampto-Southampton", "2-0"],
      ["Chelsea-Liverpool", "1-1"],
      ["Cardiff City-Burnley", "1-2"],
      ["AFC Bournemo-Crystal Pala", "2-1"]
    ],
    "6": [
      ["Fulham-Watford", "1-1"],
      ["Burnley-AFC Bournemo", "4-0"],
      ["Cardiff City-Manchester C", "0-5"],
      ["Crystal Pala-Newcastle Un", "0-0"],
      ["Leicester Ci-Huddersfield", "3-1"],
      ["Liverpool-Southampton", "3-0"],
      ["Manchester U-Wolverhampto", "1-1"],
      ["Brighton   H-Tottenham Ho", "1-2"],
      ["West Ham Uni-Chelsea", "0-0"],
      ["Arsenal-Everton", "2-0"]
    ],
    "9": [
      ["AFC Bournemo-Southampton", "0-0"],
      ["Arsenal-Leicester Ci", "3-1"],
      ["Cardiff City-Fulham", "4-2"],
      ["Chelsea-Manchester U", "2-2"],
      ["Everton-Crystal Pala", "2-0"],
      ["Huddersfield-Liverpool", "0-1"],
      ["Manchester C-Burnley", "5-0"],
      ["Newcastle Un-Brighton   H", "0-1"],
      ["West Ham Uni-Tottenham Ho", "0-1"],
      ["Wolverhampto-Watford", "0-2"]
    ],
    "8": [
      ["Brighton   H-West Ham Uni", "1-0"],
      ["Burnley-Huddersfield", "1-1"],
      ["Crystal Pala-Wolverhampto", "0-1"],
      ["Fulham-Arsenal", "1-5"],
      ["Leicester Ci-Everton", "1-2"],
      ["Liverpool-Manchester C", "0-0"],
      ["Manchester U-Newcastle Un", "3-2"],
      ["Southampton-Chelsea", "0-3"],
      ["Tottenham Ho-Cardiff City", "1-0"],
      ["Watford-AFC Bournemo", "0-4"]
    ],
    "12": [
      ["Arsenal-Wolverhampto", "1-1"],
      ["Cardiff City-Brighton   H", "2-1"],
      ["Chelsea-Everton", "0-0"],
      ["Crystal Pala-Tottenham Ho", "0-1"],
      ["Huddersfield-West Ham Uni", "1-1"],
      ["Leicester Ci-Burnley", "0-0"],
      ["Liverpool-Fulham", "2-0"],
      ["Manchester C-Manchester U", "3-1"],
      ["Newcastle Un-AFC Bournemo", "2-1"],
      ["Southampton-Watford", "1-1"]
    ],
    "11": [
      ["AFC Bournemo-Manchester U", "1-2"],
      ["Arsenal-Liverpool", "1-1"],
      ["Cardiff City-Leicester Ci", "0-1"],
      ["Chelsea-Crystal Pala", "3-1"],
      ["Everton-Brighton   H", "3-1"],
      ["Huddersfield-Fulham", "1-0"],
      ["Manchester C-Southampton", "6-1"],
      ["Newcastle Un-Watford", "1-0"],
      ["West Ham Uni-Burnley", "4-2"],
      ["Wolverhampto-Tottenham Ho", "2-3"]
    ],
    "10": [
      ["Brighton   H-Wolverhampto", "1-0"],
      ["Burnley-Chelsea", "0-4"],
      ["Crystal Pala-Arsenal", "2-2"],
      ["Fulham-AFC Bournemo", "0-3"],
      ["Leicester Ci-West Ham Uni", "1-1"],
      ["Liverpool-Cardiff City", "4-1"],
      ["Manchester U-Everton", "2-1"],
      ["Southampton-Newcastle Un", "0-0"],
      ["Tottenham Ho-Manchester C", "0-1"],
      ["Watford-Huddersfield", "3-0"]
    ],
    "13": [
      ["AFC Bournemo-Arsenal", ""],
      ["Brighton   H-Leicester Ci", ""],
      ["Burnley-Newcastle Un", ""],
      ["Everton-Cardiff City", ""],
      ["Fulham-Southampton", ""],
      ["Manchester U-Crystal Pala", ""],
      ["Tottenham Ho-Chelsea", ""],
      ["Watford-Liverpool", ""],
      ["West Ham Uni-Manchester C", ""],
      ["Wolverhampto-Huddersfield", ""]
    ],
    "38": [
      ["Brighton   H-Manchester C", ""],
      ["Burnley-Arsenal", ""],
      ["Crystal Pala-AFC Bournemo", ""],
      ["Fulham-Newcastle Un", ""],
      ["Leicester Ci-Chelsea", ""],
      ["Liverpool-Wolverhampto", ""],
      ["Manchester U-Cardiff City", ""],
      ["Southampton-Huddersfield", ""],
      ["Tottenham Ho-Everton", ""],
      ["Watford-West Ham Uni", ""]
    ],
    "15": [
      ["AFC Bournemo-Huddersfield", ""],
      ["Brighton   H-Crystal Pala", ""],
      ["Burnley-Liverpool", ""],
      ["Fulham-Leicester Ci", ""],
      ["Watford-Manchester C", ""],
      ["West Ham Uni-Cardiff City", ""],
      ["Wolverhampto-Chelsea", ""],
      ["Manchester U-Arsenal", ""],
      ["Everton-Newcastle Un", ""],
      ["Tottenham Ho-Southampton", ""]
    ],
    "14": [
      ["Arsenal-Tottenham Ho", ""],
      ["Cardiff City-Wolverhampto", ""],
      ["Chelsea-Fulham", ""],
      ["Crystal Pala-Burnley", ""],
      ["Huddersfield-Brighton   H", ""],
      ["Leicester Ci-Watford", ""],
      ["Liverpool-Everton", ""],
      ["Manchester C-AFC Bournemo", ""],
      ["Newcastle Un-West Ham Uni", ""],
      ["Southampton-Manchester U", ""]
    ],
    "17": [
      ["Brighton   H-Chelsea", ""],
      ["Crystal Pala-Leicester Ci", ""],
      ["Fulham-West Ham Uni", ""],
      ["Huddersfield-Newcastle Un", ""],
      ["Liverpool-Manchester U", ""],
      ["Manchester C-Everton", ""],
      ["Southampton-Arsenal", ""],
      ["Tottenham Ho-Burnley", ""],
      ["Watford-Cardiff City", ""],
      ["Wolverhampto-AFC Bournemo", ""]
    ],
    "16": [
      ["AFC Bournemo-Liverpool", ""],
      ["Arsenal-Huddersfield", ""],
      ["Burnley-Brighton   H", ""],
      ["Cardiff City-Southampton", ""],
      ["Chelsea-Manchester C", ""],
      ["Everton-Watford", ""],
      ["Leicester Ci-Tottenham Ho", ""],
      ["Manchester U-Fulham", ""],
      ["Newcastle Un-Wolverhampto", ""],
      ["West Ham Uni-Crystal Pala", ""]
    ],
    "19": [
      ["Brighton   H-Arsenal", ""],
      ["Burnley-Everton", ""],
      ["Crystal Pala-Cardiff City", ""],
      ["Fulham-Wolverhampto", ""],
      ["Leicester Ci-Manchester C", ""],
      ["Liverpool-Newcastle Un", ""],
      ["Manchester U-Huddersfield", ""],
      ["Southampton-West Ham Uni", ""],
      ["Tottenham Ho-AFC Bournemo", ""],
      ["Watford-Chelsea", ""]
    ],
    "18": [
      ["AFC Bournemo-Brighton   H", ""],
      ["Arsenal-Burnley", ""],
      ["Cardiff City-Manchester U", ""],
      ["Chelsea-Leicester Ci", ""],
      ["Everton-Tottenham Ho", ""],
      ["Huddersfield-Southampton", ""],
      ["Manchester C-Crystal Pala", ""],
      ["Newcastle Un-Fulham", ""],
      ["West Ham Uni-Watford", ""],
      ["Wolverhampto-Liverpool", ""]
    ],
    "31": [
      ["AFC Bournemo-Newcastle Un", ""],
      ["Brighton   H-Cardiff City", ""],
      ["Burnley-Leicester Ci", ""],
      ["Everton-Chelsea", ""],
      ["Fulham-Liverpool", ""],
      ["Manchester U-Manchester C", ""],
      ["Tottenham Ho-Crystal Pala", ""],
      ["Watford-Southampton", ""],
      ["West Ham Uni-Huddersfield", ""],
      ["Wolverhampto-Arsenal", ""]
    ],
    "30": [
      ["Arsenal-Manchester U", ""],
      ["Cardiff City-West Ham Uni", ""],
      ["Chelsea-Wolverhampto", ""],
      ["Crystal Pala-Brighton   H", ""],
      ["Huddersfield-AFC Bournemo", ""],
      ["Leicester Ci-Fulham", ""],
      ["Liverpool-Burnley", ""],
      ["Manchester C-Watford", ""],
      ["Newcastle Un-Everton", ""],
      ["Southampton-Tottenham Ho", ""]
    ],
    "37": [
      ["AFC Bournemo-Tottenham Ho", ""],
      ["Arsenal-Brighton   H", ""],
      ["Cardiff City-Crystal Pala", ""],
      ["Chelsea-Watford", ""],
      ["Everton-Burnley", ""],
      ["Huddersfield-Manchester U", ""],
      ["Manchester C-Leicester Ci", ""],
      ["Newcastle Un-Liverpool", ""],
      ["West Ham Uni-Southampton", ""],
      ["Wolverhampto-Fulham", ""]
    ],
    "36": [
      ["Brighton   H-Newcastle Un", ""],
      ["Burnley-Manchester C", ""],
      ["Crystal Pala-Everton", ""],
      ["Fulham-Cardiff City", ""],
      ["Leicester Ci-Arsenal", ""],
      ["Liverpool-Huddersfield", ""],
      ["Manchester U-Chelsea", ""],
      ["Southampton-AFC Bournemo", ""],
      ["Tottenham Ho-West Ham Uni", ""],
      ["Watford-Wolverhampto", ""]
    ],
    "35": [
      ["AFC Bournemo-Fulham", ""],
      ["Arsenal-Crystal Pala", ""],
      ["Cardiff City-Liverpool", ""],
      ["Chelsea-Burnley", ""],
      ["Everton-Manchester U", ""],
      ["Huddersfield-Watford", ""],
      ["Manchester C-Tottenham Ho", ""],
      ["Newcastle Un-Southampton", ""],
      ["West Ham Uni-Leicester Ci", ""],
      ["Wolverhampto-Brighton   H", ""]
    ],
    "34": [
      ["Brighton   H-AFC Bournemo", ""],
      ["Burnley-Cardiff City", ""],
      ["Crystal Pala-Manchester C", ""],
      ["Fulham-Everton", ""],
      ["Leicester Ci-Newcastle Un", ""],
      ["Liverpool-Chelsea", ""],
      ["Manchester U-West Ham Uni", ""],
      ["Southampton-Wolverhampto", ""],
      ["Tottenham Ho-Huddersfield", ""],
      ["Watford-Arsenal", ""]
    ],
    "33": [
      ["AFC Bournemo-Burnley", ""],
      ["Chelsea-West Ham Uni", ""],
      ["Everton-Arsenal", ""],
      ["Huddersfield-Leicester Ci", ""],
      ["Manchester C-Cardiff City", ""],
      ["Newcastle Un-Crystal Pala", ""],
      ["Southampton-Liverpool", ""],
      ["Tottenham Ho-Brighton   H", ""],
      ["Watford-Fulham", ""],
      ["Wolverhampto-Manchester U", ""]
    ],
    "32": [
      ["Arsenal-Newcastle Un", ""],
      ["Brighton   H-Southampton", ""],
      ["Burnley-Wolverhampto", ""],
      ["Cardiff City-Chelsea", ""],
      ["Crystal Pala-Huddersfield", ""],
      ["Fulham-Manchester C", ""],
      ["Leicester Ci-AFC Bournemo", ""],
      ["Liverpool-Tottenham Ho", ""],
      ["Manchester U-Watford", ""],
      ["West Ham Uni-Everton", ""]
    ]
  },
  "teamgames": {
    "Southampton": [
      ["Southampton-Burnley", "0-0"],
      ["Everton-Southampton", "2-1"],
      ["Southampton-Leicester Ci", "1-2"],
      ["Crystal Pala-Southampton", "0-2"],
      ["Southampton-Brighton   H", "2-2"],
      ["Liverpool-Southampton", "3-0"],
      ["Wolverhampto-Southampton", "2-0"],
      ["Southampton-Chelsea", "0-3"],
      ["AFC Bournemo-Southampton", "0-0"],
      ["Southampton-Newcastle Un", "0-0"],
      ["Manchester C-Southampton", "6-1"]
    ],
    "Crystal Pala": [
      ["Fulham-Crystal Pala", "0-2"],
      ["Crystal Pala-Liverpool", "0-2"],
      ["Watford-Crystal Pala", "2-1"],
      ["Crystal Pala-Southampton", "0-2"],
      ["Huddersfield-Crystal Pala", "0-1"],
      ["Crystal Pala-Newcastle Un", "0-0"],
      ["AFC Bournemo-Crystal Pala", "2-1"],
      ["Crystal Pala-Wolverhampto", "0-1"],
      ["Everton-Crystal Pala", "2-0"],
      ["Crystal Pala-Arsenal", "2-2"],
      ["Chelsea-Crystal Pala", "3-1"]
    ],
    "Liverpool": [
      ["Liverpool-West Ham Uni", "4-0"],
      ["Crystal Pala-Liverpool", "0-2"],
      ["Liverpool-Brighton   H", "1-0"],
      ["Leicester Ci-Liverpool", "1-2"],
      ["Tottenham Ho-Liverpool", "1-2"],
      ["Liverpool-Southampton", "3-0"],
      ["Chelsea-Liverpool", "1-1"],
      ["Liverpool-Manchester C", "0-0"],
      ["Huddersfield-Liverpool", "0-1"],
      ["Liverpool-Cardiff City", "4-1"],
      ["Arsenal-Liverpool", "1-1"]
    ],
    "AFC Bournemo": [
      ["AFC Bournemo-Cardiff City", "2-0"],
      ["West Ham Uni-AFC Bournemo", "1-2"],
      ["AFC Bournemo-Everton", "2-2"],
      ["Chelsea-AFC Bournemo", "2-0"],
      ["AFC Bournemo-Leicester Ci", "4-2"],
      ["Burnley-AFC Bournemo", "4-0"],
      ["AFC Bournemo-Crystal Pala", "2-1"],
      ["Watford-AFC Bournemo", "0-4"],
      ["AFC Bournemo-Southampton", "0-0"],
      ["Fulham-AFC Bournemo", "0-3"],
      ["AFC Bournemo-Manchester U", "1-2"]
    ],
    "Burnley": [
      ["Southampton-Burnley", "0-0"],
      ["Burnley-Watford", "1-3"],
      ["Fulham-Burnley", "4-2"],
      ["Burnley-Manchester U", "0-2"],
      ["Wolverhampto-Burnley", "1-0"],
      ["Burnley-AFC Bournemo", "4-0"],
      ["Cardiff City-Burnley", "1-2"],
      ["Burnley-Huddersfield", "1-1"],
      ["Manchester C-Burnley", "5-0"],
      ["Burnley-Chelsea", "0-4"],
      ["West Ham Uni-Burnley", "4-2"]
    ],
    "Manchester U": [
      ["Manchester U-Leicester Ci", "2-1"],
      ["Brighton   H-Manchester U", "3-2"],
      ["Manchester U-Tottenham Ho", "0-3"],
      ["Burnley-Manchester U", "0-2"],
      ["Watford-Manchester U", "1-2"],
      ["Manchester U-Wolverhampto", "1-1"],
      ["West Ham Uni-Manchester U", "3-1"],
      ["Manchester U-Newcastle Un", "3-2"],
      ["Chelsea-Manchester U", "2-2"],
      ["Manchester U-Everton", "2-1"],
      ["AFC Bournemo-Manchester U", "1-2"]
    ],
    "Wolverhampto": [
      ["Wolverhampto-Everton", "2-2"],
      ["Leicester Ci-Wolverhampto", "2-0"],
      ["Wolverhampto-Manchester C", "1-1"],
      ["West Ham Uni-Wolverhampto", "0-1"],
      ["Wolverhampto-Burnley", "1-0"],
      ["Manchester U-Wolverhampto", "1-1"],
      ["Wolverhampto-Southampton", "2-0"],
      ["Crystal Pala-Wolverhampto", "0-1"],
      ["Wolverhampto-Watford", "0-2"],
      ["Brighton   H-Wolverhampto", "1-0"],
      ["Wolverhampto-Tottenham Ho", "2-3"]
    ],
    "West Ham Uni": [
      ["Liverpool-West Ham Uni", "4-0"],
      ["West Ham Uni-AFC Bournemo", "1-2"],
      ["Arsenal-West Ham Uni", "3-1"],
      ["West Ham Uni-Wolverhampto", "0-1"],
      ["Everton-West Ham Uni", "1-3"],
      ["West Ham Uni-Chelsea", "0-0"],
      ["West Ham Uni-Manchester U", "3-1"],
      ["Brighton   H-West Ham Uni", "1-0"],
      ["West Ham Uni-Tottenham Ho", "0-1"],
      ["Leicester Ci-West Ham Uni", "1-1"],
      ["West Ham Uni-Burnley", "4-2"]
    ],
    "Manchester C": [
      ["Arsenal-Manchester C", "0-2"],
      ["Manchester C-Huddersfield", "6-1"],
      ["Wolverhampto-Manchester C", "1-1"],
      ["Manchester C-Newcastle Un", "2-1"],
      ["Manchester C-Fulham", "3-0"],
      ["Cardiff City-Manchester C", "0-5"],
      ["Manchester C-Brighton   H", "2-0"],
      ["Liverpool-Manchester C", "0-0"],
      ["Manchester C-Burnley", "5-0"],
      ["Tottenham Ho-Manchester C", "0-1"],
      ["Manchester C-Southampton", "6-1"]
    ],
    "Arsenal": [
      ["Arsenal-Manchester C", "0-2"],
      ["Chelsea-Arsenal", "3-2"],
      ["Arsenal-West Ham Uni", "3-1"],
      ["Cardiff City-Arsenal", "2-3"],
      ["Newcastle Un-Arsenal", "1-2"],
      ["Arsenal-Everton", "2-0"],
      ["Arsenal-Watford", "2-0"],
      ["Fulham-Arsenal", "1-5"],
      ["Arsenal-Leicester Ci", "3-1"],
      ["Crystal Pala-Arsenal", "2-2"],
      ["Arsenal-Liverpool", "1-1"]
    ],
    "Newcastle Un": [
      ["Newcastle Un-Tottenham Ho", "1-2"],
      ["Cardiff City-Newcastle Un", "0-0"],
      ["Newcastle Un-Chelsea", "1-2"],
      ["Manchester C-Newcastle Un", "2-1"],
      ["Newcastle Un-Arsenal", "1-2"],
      ["Crystal Pala-Newcastle Un", "0-0"],
      ["Newcastle Un-Leicester Ci", "0-2"],
      ["Manchester U-Newcastle Un", "3-2"],
      ["Newcastle Un-Brighton   H", "0-1"],
      ["Southampton-Newcastle Un", "0-0"],
      ["Newcastle Un-Watford", "1-0"]
    ],
    "Leicester Ci": [
      ["Manchester U-Leicester Ci", "2-1"],
      ["Leicester Ci-Wolverhampto", "2-0"],
      ["Southampton-Leicester Ci", "1-2"],
      ["Leicester Ci-Liverpool", "1-2"],
      ["AFC Bournemo-Leicester Ci", "4-2"],
      ["Leicester Ci-Huddersfield", "3-1"],
      ["Newcastle Un-Leicester Ci", "0-2"],
      ["Leicester Ci-Everton", "1-2"],
      ["Arsenal-Leicester Ci", "3-1"],
      ["Leicester Ci-West Ham Uni", "1-1"],
      ["Cardiff City-Leicester Ci", "0-1"]
    ],
    "Fulham": [
      ["Fulham-Crystal Pala", "0-2"],
      ["Tottenham Ho-Fulham", "3-1"],
      ["Fulham-Burnley", "4-2"],
      ["Brighton   H-Fulham", "2-2"],
      ["Manchester C-Fulham", "3-0"],
      ["Fulham-Watford", "1-1"],
      ["Everton-Fulham", "3-0"],
      ["Fulham-Arsenal", "1-5"],
      ["Cardiff City-Fulham", "4-2"],
      ["Fulham-AFC Bournemo", "0-3"],
      ["Huddersfield-Fulham", "1-0"]
    ],
    "Watford": [
      ["Watford-Brighton   H", "2-0"],
      ["Burnley-Watford", "1-3"],
      ["Watford-Crystal Pala", "2-1"],
      ["Watford-Tottenham Ho", "2-1"],
      ["Watford-Manchester U", "1-2"],
      ["Fulham-Watford", "1-1"],
      ["Arsenal-Watford", "2-0"],
      ["Watford-AFC Bournemo", "0-4"],
      ["Wolverhampto-Watford", "0-2"],
      ["Watford-Huddersfield", "3-0"],
      ["Newcastle Un-Watford", "1-0"]
    ],
    "Tottenham Ho": [
      ["Newcastle Un-Tottenham Ho", "1-2"],
      ["Tottenham Ho-Fulham", "3-1"],
      ["Manchester U-Tottenham Ho", "0-3"],
      ["Watford-Tottenham Ho", "2-1"],
      ["Tottenham Ho-Liverpool", "1-2"],
      ["Brighton   H-Tottenham Ho", "1-2"],
      ["Huddersfield-Tottenham Ho", "0-2"],
      ["Tottenham Ho-Cardiff City", "1-0"],
      ["West Ham Uni-Tottenham Ho", "0-1"],
      ["Tottenham Ho-Manchester C", "0-1"],
      ["Wolverhampto-Tottenham Ho", "2-3"]
    ],
    "Everton": [
      ["Wolverhampto-Everton", "2-2"],
      ["Everton-Southampton", "2-1"],
      ["AFC Bournemo-Everton", "2-2"],
      ["Everton-Huddersfield", "1-1"],
      ["Everton-West Ham Uni", "1-3"],
      ["Arsenal-Everton", "2-0"],
      ["Everton-Fulham", "3-0"],
      ["Leicester Ci-Everton", "1-2"],
      ["Everton-Crystal Pala", "2-0"],
      ["Manchester U-Everton", "2-1"],
      ["Everton-Brighton   H", "3-1"]
    ],
    "Cardiff City": [
      ["AFC Bournemo-Cardiff City", "2-0"],
      ["Cardiff City-Newcastle Un", "0-0"],
      ["Huddersfield-Cardiff City", "0-0"],
      ["Cardiff City-Arsenal", "2-3"],
      ["Chelsea-Cardiff City", "4-1"],
      ["Cardiff City-Manchester C", "0-5"],
      ["Cardiff City-Burnley", "1-2"],
      ["Tottenham Ho-Cardiff City", "1-0"],
      ["Cardiff City-Fulham", "4-2"],
      ["Liverpool-Cardiff City", "4-1"],
      ["Cardiff City-Leicester Ci", "0-1"]
    ],
    "Brighton   H": [
      ["Watford-Brighton   H", "2-0"],
      ["Brighton   H-Manchester U", "3-2"],
      ["Liverpool-Brighton   H", "1-0"],
      ["Brighton   H-Fulham", "2-2"],
      ["Southampton-Brighton   H", "2-2"],
      ["Brighton   H-Tottenham Ho", "1-2"],
      ["Manchester C-Brighton   H", "2-0"],
      ["Brighton   H-West Ham Uni", "1-0"],
      ["Newcastle Un-Brighton   H", "0-1"],
      ["Brighton   H-Wolverhampto", "1-0"],
      ["Everton-Brighton   H", "3-1"]
    ],
    "Chelsea": [
      ["Huddersfield-Chelsea", "0-3"],
      ["Chelsea-Arsenal", "3-2"],
      ["Newcastle Un-Chelsea", "1-2"],
      ["Chelsea-AFC Bournemo", "2-0"],
      ["Chelsea-Cardiff City", "4-1"],
      ["West Ham Uni-Chelsea", "0-0"],
      ["Chelsea-Liverpool", "1-1"],
      ["Southampton-Chelsea", "0-3"],
      ["Chelsea-Manchester U", "2-2"],
      ["Burnley-Chelsea", "0-4"],
      ["Chelsea-Crystal Pala", "3-1"]
    ],
    "Huddersfield": [
      ["Huddersfield-Chelsea", "0-3"],
      ["Manchester C-Huddersfield", "6-1"],
      ["Huddersfield-Cardiff City", "0-0"],
      ["Everton-Huddersfield", "1-1"],
      ["Huddersfield-Crystal Pala", "0-1"],
      ["Leicester Ci-Huddersfield", "3-1"],
      ["Huddersfield-Tottenham Ho", "0-2"],
      ["Burnley-Huddersfield", "1-1"],
      ["Huddersfield-Liverpool", "0-1"],
      ["Watford-Huddersfield", "3-0"],
      ["Huddersfield-Fulham", "1-0"]
    ]
  },
  "teams": {
    "england": [
      "Liverpool",
      "Crystal Pala",
      "Brighton   H",
      "Watford",
      "AFC Bournemo",
      "Burnley",
      "Southampton",
      "Manchester U",
      "Wolverhampto",
      "Fulham",
      "Manchester C",
      "West Ham Uni",
      "Leicester Ci",
      "Newcastle Un",
      "Cardiff City",
      "Arsenal",
      "Tottenham Ho",
      "Everton",
      "Huddersfield",
      "Chelsea"
    ]
  }
}
